nvshmem/__init__.py
nvshmem/version.py
nvshmem/bindings/__init__.py
nvshmem/bindings/cynvshmem.cpp
nvshmem/bindings/cynvshmem.cpython-310-aarch64-linux-gnu.so
nvshmem/bindings/cynvshmem.pxd
nvshmem/bindings/cynvshmem.pyx
nvshmem/bindings/nvshmem.cpp
nvshmem/bindings/nvshmem.cpython-310-aarch64-linux-gnu.so
nvshmem/bindings/nvshmem.pxd
nvshmem/bindings/nvshmem.pyx
nvshmem/bindings/_internal/__init__.py
nvshmem/bindings/_internal/nvshmem.cpp
nvshmem/bindings/_internal/nvshmem.cpython-310-aarch64-linux-gnu.so
nvshmem/bindings/_internal/nvshmem.pxd
nvshmem/bindings/_internal/nvshmem.pyx
nvshmem/bindings/_internal/nvshmem_linux.pyx
nvshmem/core/__init__.py
nvshmem/core/_internal_tracking.py
nvshmem/core/collective.py
nvshmem/core/direct.py
nvshmem/core/init_fini.py
nvshmem/core/memory.py
nvshmem/core/nvshmem_types.py
nvshmem/core/rma.py
nvshmem/core/utils.py
nvshmem/core/interop/cupy.py
nvshmem/core/interop/torch.py
nvshmem4py_cu13-0.1.2.dist-info/METADATA
nvshmem4py_cu13-0.1.2.dist-info/WHEEL
nvshmem4py_cu13-0.1.2.dist-info/top_level.txt
nvshmem4py_cu13-0.1.2.dist-info/RECORD
