Metadata-Version: 2.4
Name: nvshmem4py-cu13
Version: 0.1.2
Summary: Python bindings for NVSHMEM
Author: NVIDIA Corporation
Requires-Python: >=3.9
Requires-Dist: nvidia-nvshmem-cu13
Requires-Dist: cuda-python>=13.0
Requires-Dist: cuda.core==0.2.0
Requires-Dist: numpy
Requires-Dist: Cython>=0.29.24
Provides-Extra: dev
Requires-Dist: pytest>=6.0; extra == "dev"
Requires-Dist: black; extra == "dev"
Requires-Dist: isort; extra == "dev"
